[
  {
    "id": "options",
    "version": "v0.36.0-beta.4",
    "upstream": {
      "url": "http://resource-server:8080",
      "preserve_host": true
    },
    "match": {
      "url": "http://localhost:8004/creditors/<.*>",
      "methods": [
        "OPTIONS"
      ]
    },
    "authenticators": [
      {
        "handler": "noop"
      }
    ],
    "authorizer": {
      "handler": "allow"
    },
    "mutators": [
      {
        "handler": "noop"
      }
    ]
  },

  {
    "id": "docs",
    "version": "v0.36.0-beta.4",
    "upstream": {
      "url": "http://resource-server:8080",
      "preserve_host": true
    },
    "match": {
      "url": "http://localhost:8004/creditors/<\\.docs(/.*)?$>",
      "methods": [
        "GET", "HEAD"
      ]
    },
    "authenticators": [
      {
        "handler": "noop"
      }
    ],
    "authorizer": {
      "handler": "allow"
    },
    "mutators": [
      {
        "handler": "noop"
      }
    ]
  },

  {
    "id": "access.readonly",
    "version": "v0.36.0-beta.4",
    "upstream": {
      "url": "http://resource-server:8080",
      "preserve_host": true
    },
    "match": {
      "url": "http://localhost:8004/creditors/<(?!\\.docs(/.*)?$).*>",
      "methods": [
        "GET", "HEAD"
      ]
    },
    "authenticators": [
      {
        "handler": "oauth2_introspection",
        "config": {
          "required_scope": ["access.readonly"]
        }
      }
    ],
    "authorizer": {
      "handler": "allow"
    },
    "mutators": [
      {
        "handler": "header",
        "config": {
          "headers": {
            "X-Swpt-User-Id": "{{ print .Subject }}"
          }
        }
      }
    ]
  },

  {
    "id": "access",
    "version": "v0.36.0-beta.4",
    "upstream": {
      "url": "http://resource-server:8080",
      "preserve_host": true
    },
    "match": {
      "url": "http://localhost:8004/creditors/<(?!.*[/-](reserve|activate|deactivate)$).*>",
      "methods": [
        "POST", "PUT", "PATCH", "DELETE"
      ]
    },
    "authenticators": [
      {
        "handler": "oauth2_introspection",
        "config": {
          "required_scope": ["access"]
        }
      }
    ],
    "authorizer": {
      "handler": "allow"
    },
    "mutators": [
      {
        "handler": "header",
        "config": {
          "headers": {
            "X-Swpt-User-Id": "{{ print .Subject }}"
          }
        }
      }
    ]
  },

  {
    "id": "activate",
    "version": "v0.36.0-beta.4",
    "upstream": {
      "url": "http://resource-server:8080",
      "preserve_host": true
    },
    "match": {
      "url": "http://localhost:8004/creditors/<.*[/-](reserve|activate)$>",
      "methods": [
        "POST"
      ]
    },
    "authenticators": [
      {
        "handler": "oauth2_introspection",
        "config": {
          "required_scope": ["activate"]
        }
      }
    ],
    "authorizer": {
      "handler": "allow"
    },
    "mutators": [
      {
        "handler": "header",
        "config": {
          "headers": {
            "X-Swpt-User-Id": "{{ print .Subject }}"
          }
        }
      }
    ]
  },

  {
    "id": "deactivate",
    "version": "v0.36.0-beta.4",
    "upstream": {
      "url": "http://resource-server:8080",
      "preserve_host": true
    },
    "match": {
      "url": "http://localhost:8004/creditors/<.*[/-](deactivate)$>",
      "methods": [
        "POST"
      ]
    },
    "authenticators": [
      {
        "handler": "oauth2_introspection",
        "config": {
          "required_scope": ["deactivate"]
        }
      }
    ],
    "authorizer": {
      "handler": "allow"
    },
    "mutators": [
      {
        "handler": "header",
        "config": {
          "headers": {
            "X-Swpt-User-Id": "{{ print .Subject }}"
          }
        }
      }
    ]
  }

]
